altxria/olympus/__init__.py
altxria/olympus/exceptions_manager.py
altxria/olympus/https_enforcer.py
altxria/olympus/server.py
altxria/olympus/routing/__init__.py
altxria/olympus/routing/cors.py
altxria/olympus/routing/decorators.py
altxria/olympus/routing/exceptions.py
altxria/olympus/routing/middleware.py
altxria/olympus/routing/request.py
altxria/olympus/routing/response.py
altxria/olympus/routing/route.py
altxria/olympus/routing/router.py
olympus_framework-0.1.1.dist-info/LICENSE
olympus_framework-0.1.1.dist-info/METADATA
olympus_framework-0.1.1.dist-info/WHEEL
olympus_framework-0.1.1.dist-info/top_level.txt
olympus_framework-0.1.1.dist-info/RECORD
