Metadata-Version: 2.1
Name: olympus-framework
Version: 0.1.1
Summary: A Python web framework foundation inspired by Laravel's routing, middleware, and exception handling.
Author-email: "Altxria Inc." <company@altxria.com>
License: MIT
Project-URL: Bug Tracker, https://github.com/altxriainc/olympus/issues
Project-URL: Documentation, https://github.com/altxriainc/olympus/wiki
Project-URL: Source Code, https://github.com/altxriainc/olympus
Keywords: web,framework,routing,middleware,http,jinja2
Classifier: Development Status :: 3 - Alpha
Classifier: Intended Audience :: Developers
Classifier: License :: OSI Approved :: MIT License
Classifier: Programming Language :: Python :: 3
Classifier: Programming Language :: Python :: 3.8
Classifier: Programming Language :: Python :: 3.9
Classifier: Programming Language :: Python :: 3.10
Classifier: Programming Language :: Python :: 3.11
Classifier: Operating System :: OS Independent
Requires-Python: >=3.8
License-File: LICENSE
Provides-Extra: dev
Requires-Dist: pytest>=7.0; extra == "dev"
Requires-Dist: black>=23.0; extra == "dev"
Requires-Dist: flake8>=6.0; extra == "dev"
